MANIFEST.in
README.md
setup.py
pandastable/__init__.py
pandastable/app.py
pandastable/config.py
pandastable/core.py
pandastable/data.py
pandastable/dataexplore.gif
pandastable/dialogs.py
pandastable/handlers.py
pandastable/headers.py
pandastable/images.py
pandastable/plotting.py
pandastable/plugin.py
pandastable/stats.py
pandastable/tests.py
pandastable/util.py
pandastable.egg-info/PKG-INFO
pandastable.egg-info/SOURCES.txt
pandastable.egg-info/dependency_links.txt
pandastable.egg-info/entry_points.txt
pandastable.egg-info/requires.txt
pandastable.egg-info/top_level.txt
pandastable/../description.txt
pandastable/datasets/co2-ppm-mauna-loa.csv
pandastable/datasets/iris.csv
pandastable/datasets/miRNA.csv
pandastable/datasets/pima.csv
pandastable/datasets/tips.csv
pandastable/datasets/titanic3.csv
pandastable/datasets/zoo_dataset.csv
pandastable/plugins/DEanalysis.R
pandastable/plugins/Limma.R
pandastable/plugins/batchprocess.py
pandastable/plugins/diffexpr.py
pandastable/plugins/example.py
pandastable/plugins/ipythonview.py
pandastable/plugins/mdanalysis.py
pandastable/plugins/remotedata.py
pandastable/plugins/rename.py
pandastable/plugins/scriptrunner.py
pandastable/plugins/seabornplots.py