Metadata-Version: 1.1
Name: pandastable
Version: 0.13.0
Summary: Library for embedding tables in Tkinter using pandas DataFrames
Home-page: https://github.com/dmnfarrell/pandastable
Author: Damien Farrell
Author-email: farrell.damien@gmail.com
License: GPL v3
Keywords: tkinter,ttk,spreadsheet,table,pandas,data analysis
Platform: UNKNOWN
Classifier: Operating System :: OS Independent
Classifier: Programming Language :: Python :: 3
Classifier: Operating System :: MacOS :: MacOS X
Classifier: Operating System :: Microsoft :: Windows
Classifier: Operating System :: POSIX
Classifier: Topic :: Software Development :: User Interfaces
Classifier: License :: OSI Approved :: GNU General Public License v3 (GPLv3)
Classifier: Development Status :: 4 - Beta
Classifier: Intended Audience :: Science/Research
